KIB_LAP/__init__.py
KIB_LAP/plate_bending_cpp.cp313-win_amd64.pyd
KIB_LAP/plate_buckling_cpp.cp313-win_amd64.pyd
KIB_LAP/Betonbau/Bemessung_Polygon.py
KIB_LAP/Betonbau/Cross_Section_Kappa.py
KIB_LAP/Betonbau/Druckglied_KGV.py
KIB_LAP/Betonbau/M_K_Parametrisch.py
KIB_LAP/Betonbau/Materialkennwerte_Beton.py
KIB_LAP/Betonbau/Querschnittsbreite.py
KIB_LAP/Betonbau/Querschnittsbreite_Kreis.py
KIB_LAP/Betonbau/TEST_Rectangular.py
KIB_LAP/Betonbau/__init__.py
KIB_LAP/Betonbau/beam_plate_T.py
KIB_LAP/Betonbau/beam_plate_T_reverse.py
KIB_LAP/Betonbau/beam_rectangular.py
KIB_LAP/Betonbau/beam_sub_section.py
KIB_LAP/Dynamik/Cross_Section_Properties.py
KIB_LAP/Dynamik/Deformation_Method.py
KIB_LAP/Dynamik/Duhamel_SDOF.py
KIB_LAP/Dynamik/FFT.py
KIB_LAP/Dynamik/Kontinuum_Eigenmodes.py
KIB_LAP/Dynamik/Kontinuum_Schwingung.py
KIB_LAP/Dynamik/Pendulum_Spring_Linearized.py
KIB_LAP/Dynamik/Pendulum_Spring_Problem.py
KIB_LAP/Dynamik/__init__.py
KIB_LAP/Examples/Cross_Section_Thin.py
KIB_LAP/Examples/Cross_Section_Thin_2.py
KIB_LAP/Examples/Plattentragwerke.py
KIB_LAP/Examples/Plattentragwerke_2.py
KIB_LAP/Examples/ShearDesign.py
KIB_LAP/Examples/__init__.py
KIB_LAP/FACHWERKEBEN/Elements.py
KIB_LAP/FACHWERKEBEN/InputData.py
KIB_LAP/FACHWERKEBEN/Iteration.py
KIB_LAP/FACHWERKEBEN/Materials.py
KIB_LAP/FACHWERKEBEN/Plotting.py
KIB_LAP/FACHWERKEBEN/__init__.py
KIB_LAP/FACHWERKEBEN/main.py
KIB_LAP/Plattenbeulen/Plate_Design.py
KIB_LAP/Plattenbeulen/Ritz_Optimiert.py
KIB_LAP/Plattenbeulen/__init__.py
KIB_LAP/Plattenbeulen/plate_buckling.cpp
KIB_LAP/Plattenbeulen/plate_buckling_cpp.cp313-win_amd64.pyd
KIB_LAP/Plattenbeulen/plate_buckling_cpp.cpp
KIB_LAP/Plattenbeulen/setup.py
KIB_LAP/Plattenbeulen/dist/__init__.py
KIB_LAP/Plattentragwerke/Functions.cpp
KIB_LAP/Plattentragwerke/Functions.h
KIB_LAP/Plattentragwerke/PlateBendingKirchhoff.py
KIB_LAP/Plattentragwerke/__init__.py
KIB_LAP/Plattentragwerke/plate_bending.cpp
KIB_LAP/Plattentragwerke/setup.py
kib_lap-0.8.9.dist-info/METADATA
kib_lap-0.8.9.dist-info/WHEEL
kib_lap-0.8.9.dist-info/top_level.txt
kib_lap-0.8.9.dist-info/RECORD
