Metadata-Version: 2.1
Name: kib_lap
Version: 0.8.9
Summary: A package for structural engineering calculations
Author: leoth
Author-email: thomas.leonard@outlook.de
License: MIT
Classifier: Programming Language :: Python :: 3
Classifier: License :: OSI Approved :: MIT License
Classifier: Operating System :: OS Independent
Requires-Python: >=3.6
Requires-Dist: pybind11 >=2.6
